{
  "test_id": "SSC CGL 2021 Tier-I _Held On _ 21 April 2022 Shift 1__6960f3363cce58628df19d3d",
  "test_name": "SSC CGL 2021 Tier-I _Held On _ 21 April 2022 Shift 1__6960f3363cce58628df19d3d",
  "failed_at": "2026-01-26 14:25:18",
  "failed_questions": [
    {
      "question_id": "62744907f60b60bce391ad12",
      "section": "General Intelligence and Reasoning",
      "status": "partial",
      "has_english": true,
      "has_hindi": false
    },
    {
      "question_id": "62744ae9292c4dfc2e6a3936",
      "section": "General Intelligence and Reasoning",
      "status": "partial",
      "has_english": true,
      "has_hindi": false
    },
    {
      "question_id": "6274549f292c4dfc2e6a9253",
      "section": "Quantitative Aptitude",
      "status": "failed",
      "has_english": false,
      "has_hindi": false
    },
    {
      "question_id": "627455baf60b60bce3922b3a",
      "section": "Quantitative Aptitude",
      "status": "partial",
      "has_english": true,
      "has_hindi": false
    },
    {
      "question_id": "627455f3292c4dfc2e6a9d37",
      "section": "Quantitative Aptitude",
      "status": "partial",
      "has_english": true,
      "has_hindi": false
    },
    {
      "question_id": "6274570af60b60bce392387a",
      "section": "Quantitative Aptitude",
      "status": "partial",
      "has_english": true,
      "has_hindi": false
    },
    {
      "question_id": "62745737292c4dfc2e6aa744",
      "section": "Quantitative Aptitude",
      "status": "partial",
      "has_english": true,
      "has_hindi": false
    },
    {
      "question_id": "62745a18292c4dfc2e6ac217",
      "section": "Quantitative Aptitude",
      "status": "partial",
      "has_english": false,
      "has_hindi": true
    },
    {
      "question_id": "62745c56f60b60bce3927108",
      "section": "Quantitative Aptitude",
      "status": "failed",
      "has_english": false,
      "has_hindi": false
    },
    {
      "question_id": "627469cdf60b60bce39311fa",
      "section": "English Comprehension",
      "status": "partial",
      "has_english": true,
      "has_hindi": false
    },
    {
      "question_id": "627469f6292c4dfc2e6b7a36",
      "section": "English Comprehension",
      "status": "partial",
      "has_english": true,
      "has_hindi": false
    },
    {
      "question_id": "62746a24a6b8d61b7173c56f",
      "section": "English Comprehension",
      "status": "partial",
      "has_english": true,
      "has_hindi": false
    },
    {
      "question_id": "62746a57a6b8d61b7173c6c9",
      "section": "English Comprehension",
      "status": "partial",
      "has_english": true,
      "has_hindi": false
    },
    {
      "question_id": "62746a90f60b60bce3931b32",
      "section": "English Comprehension",
      "status": "partial",
      "has_english": true,
      "has_hindi": false
    },
    {
      "question_id": "62746ae2a6b8d61b7173cd79",
      "section": "English Comprehension",
      "status": "partial",
      "has_english": true,
      "has_hindi": false
    },
    {
      "question_id": "62746b0947255b668d9320a0",
      "section": "English Comprehension",
      "status": "partial",
      "has_english": true,
      "has_hindi": false
    },
    {
      "question_id": "62746b44f60b60bce3932460",
      "section": "English Comprehension",
      "status": "partial",
      "has_english": true,
      "has_hindi": false
    },
    {
      "question_id": "62746b98f60b60bce39329bc",
      "section": "English Comprehension",
      "status": "partial",
      "has_english": true,
      "has_hindi": false
    },
    {
      "question_id": "62746bcef60b60bce3932ccc",
      "section": "English Comprehension",
      "status": "partial",
      "has_english": true,
      "has_hindi": false
    },
    {
      "question_id": "62746c2747255b668d932f53",
      "section": "English Comprehension",
      "status": "partial",
      "has_english": true,
      "has_hindi": false
    },
    {
      "question_id": "62746c8c292c4dfc2e6ba0c1",
      "section": "English Comprehension",
      "status": "partial",
      "has_english": true,
      "has_hindi": false
    },
    {
      "question_id": "62746cc532b227724a29261b",
      "section": "English Comprehension",
      "status": "partial",
      "has_english": true,
      "has_hindi": false
    },
    {
      "question_id": "62746d0cf60b60bce3934365",
      "section": "English Comprehension",
      "status": "partial",
      "has_english": true,
      "has_hindi": false
    },
    {
      "question_id": "62746d88af0fc33d28172760",
      "section": "English Comprehension",
      "status": "partial",
      "has_english": true,
      "has_hindi": false
    }
  ],
  "summary": {
    "total_questions": 100,
    "successful": 76,
    "skipped": 0,
    "failed": 2,
    "partial": 22
  }
}