{
  "test_id": "SSC CGL 2021 Tier-I _Held On _ 18 April 2022 Shift 3__6960f33b0300ada7a28fef05",
  "test_name": "SSC CGL 2021 Tier-I _Held On _ 18 April 2022 Shift 3__6960f33b0300ada7a28fef05",
  "failed_at": "2026-01-26 14:20:02",
  "failed_questions": [
    {
      "question_id": "6274ccac1bde985bc4ca7699",
      "section": "Quantitative Aptitude",
      "status": "partial",
      "has_english": false,
      "has_hindi": true
    },
    {
      "question_id": "6274d1646e08d3aa09f881fd",
      "section": "Quantitative Aptitude",
      "status": "failed",
      "has_english": false,
      "has_hindi": false
    },
    {
      "question_id": "6274d73401d91c23bada9abf",
      "section": "Quantitative Aptitude",
      "status": "partial",
      "has_english": true,
      "has_hindi": false
    },
    {
      "question_id": "6274deda6e08d3aa09fa2819",
      "section": "Quantitative Aptitude",
      "status": "partial",
      "has_english": false,
      "has_hindi": true
    },
    {
      "question_id": "6274e0356e08d3aa09fa5098",
      "section": "Quantitative Aptitude",
      "status": "failed",
      "has_english": false,
      "has_hindi": false
    },
    {
      "question_id": "6274e2cd32b227724a2cc7ba",
      "section": "Quantitative Aptitude",
      "status": "partial",
      "has_english": true,
      "has_hindi": false
    },
    {
      "question_id": "6274e47a723e401fdd0eb372",
      "section": "Quantitative Aptitude",
      "status": "partial",
      "has_english": true,
      "has_hindi": false
    },
    {
      "question_id": "6274e74c33bffbc254722de4",
      "section": "Quantitative Aptitude",
      "status": "partial",
      "has_english": true,
      "has_hindi": false
    },
    {
      "question_id": "6274efec2c22b3f3f836adf3",
      "section": "Quantitative Aptitude",
      "status": "partial",
      "has_english": true,
      "has_hindi": false
    },
    {
      "question_id": "6274f360723e401fdd108022",
      "section": "Quantitative Aptitude",
      "status": "partial",
      "has_english": true,
      "has_hindi": false
    },
    {
      "question_id": "627527b6c36dd5ebbf426265",
      "section": "Quantitative Aptitude",
      "status": "partial",
      "has_english": true,
      "has_hindi": false
    },
    {
      "question_id": "62752848d35f22ccdec39dcd",
      "section": "English Comprehension",
      "status": "partial",
      "has_english": true,
      "has_hindi": false
    },
    {
      "question_id": "62752936285888fe65525294",
      "section": "English Comprehension",
      "status": "partial",
      "has_english": true,
      "has_hindi": false
    },
    {
      "question_id": "627529a5713917cb05336ca1",
      "section": "English Comprehension",
      "status": "partial",
      "has_english": true,
      "has_hindi": false
    },
    {
      "question_id": "62752a091bde985bc4d62425",
      "section": "English Comprehension",
      "status": "partial",
      "has_english": true,
      "has_hindi": false
    },
    {
      "question_id": "62752a736c8e2d3d1a6cf524",
      "section": "English Comprehension",
      "status": "partial",
      "has_english": true,
      "has_hindi": false
    },
    {
      "question_id": "62752accc36dd5ebbf42ba1f",
      "section": "English Comprehension",
      "status": "partial",
      "has_english": true,
      "has_hindi": false
    },
    {
      "question_id": "62752b21723e401fdd17788b",
      "section": "English Comprehension",
      "status": "partial",
      "has_english": true,
      "has_hindi": false
    },
    {
      "question_id": "62752bca6e08d3aa0903a327",
      "section": "English Comprehension",
      "status": "partial",
      "has_english": true,
      "has_hindi": false
    },
    {
      "question_id": "62752c23d35f22ccdec3fe33",
      "section": "English Comprehension",
      "status": "partial",
      "has_english": true,
      "has_hindi": false
    },
    {
      "question_id": "62752c892c22b3f3f83e41d1",
      "section": "English Comprehension",
      "status": "partial",
      "has_english": true,
      "has_hindi": false
    },
    {
      "question_id": "62752ce8285888fe6552abc1",
      "section": "English Comprehension",
      "status": "partial",
      "has_english": true,
      "has_hindi": false
    },
    {
      "question_id": "62752d23713917cb0533c31e",
      "section": "English Comprehension",
      "status": "partial",
      "has_english": true,
      "has_hindi": false
    },
    {
      "question_id": "62752d8fc656e1b8d8f629c7",
      "section": "English Comprehension",
      "status": "partial",
      "has_english": true,
      "has_hindi": false
    },
    {
      "question_id": "62752ddc2c22b3f3f83e6351",
      "section": "English Comprehension",
      "status": "partial",
      "has_english": true,
      "has_hindi": false
    },
    {
      "question_id": "62752e42c36dd5ebbf43159e",
      "section": "English Comprehension",
      "status": "partial",
      "has_english": true,
      "has_hindi": false
    }
  ],
  "summary": {
    "total_questions": 100,
    "successful": 74,
    "skipped": 0,
    "failed": 2,
    "partial": 24
  }
}