{
  "page_number": 191,
  "timestamp": "2026-01-26T04:10:50.466472",
  "questions": [
    {
      "question_hindi": "निम्नलिखित रानियों में से किसने सिक्के चलवाए?",
      "options_hindi": [
        "ध्रुवदेवी",
        "दिद्दा",
        "उपरोक्त दोनों",
        "इनमें से कोई नहीं"
      ],
      "option_labels": [
        "अ",
        "ब",
        "स",
        "द"
      ],
      "source": "bharatkosh",
      "page_number": 191,
      "question_number": 1,
      "subject": "इतिहास (History)",
      "language": "hindi",
      "question_english": "Which of the following queens issued coins?",
      "options_english": [
        "Dhrudevi",
        "Didda",
        "Both of the above",
        "None of these"
      ],
      "correct_answer": "b",
      "explanation_english": "Didda, a queen of the Kashmiri Pandit dynasty in the 10th century, is historically documented to have issued coins in her own name, which is a rare phenomenon for queens in medieval India. Dhrudevi, the queen of the Chalukya dynasty, is not known to have issued coins. The issuance of coins by Didda signifies her administrative authority and the unique status of women in certain regional dynasties.",
      "explanation_hindi": "दिद्दा, 10वीं शताब्दी में कश्मीरी पंडित वंश की रानी थीं, जिन्होंने अपने नाम पर सिक्के जारी किए, जो मध्यकालीन भारत में रानियों के लिए असामान्य घटना है। ध्रुवदेवी, जो चालुक्य वंश की रानी थीं, के सिक्कों का कोई ऐतिहासिक साक्ष्य नहीं है। दिद्दा द्वारा सिक्कों के जारी करने से उनकी प्रशासनिक शक्ति और कुछ क्षेत्रीय वंशों में महिलाओं की विशिष्ट स्थिति के बारे में ज्ञान होता है।",
      "topic": "Medieval Indian History",
      "difficulty": "medium",
      "key_facts": [
        "Didda issued coins in her own name in the 10th century, a rare occurrence for queens in medieval India.",
        "Dhrudevi of the Chalukya dynasty is not historically linked to coin issuance."
      ],
      "ai_processed": true,
      "processed_at": "2026-01-26T04:09:40.611152"
    },
    {
      "question_hindi": "निम्न में से कौन-सा सूबाबादशाह जहाँगीरके काल में बना था?",
      "options_hindi": [
        "सिंध",
        "उड़ीसा",
        "कश्मीर",
        "बीजापुर"
      ],
      "option_labels": [
        "अ",
        "ब",
        "स",
        "द"
      ],
      "source": "bharatkosh",
      "page_number": 191,
      "question_number": 2,
      "subject": "इतिहास (History)",
      "language": "hindi",
      "ai_processed": false,
      "error": "Expecting value: line 1 column 1 (char 0)"
    },
    {
      "question_hindi": "‘मत्तविलास प्रहसन’नामकनाटकके रचयिता कौन थे?",
      "options_hindi": [
        "हर्ष",
        "राज राजेन्द्र",
        "जयदेव",
        "महेन्द्र वर्मन प्रथम"
      ],
      "option_labels": [
        "अ",
        "ब",
        "स",
        "द"
      ],
      "source": "bharatkosh",
      "page_number": 191,
      "question_number": 3,
      "subject": "इतिहास (History)",
      "language": "hindi",
      "question_english": "Who was the author of the play 'Mattavilasa Prahasana'?",
      "options_english": [
        "Harsha",
        "Raj Rajendra",
        "Jayadeva",
        "Mahendra Varman I"
      ],
      "correct_answer": "d",
      "explanation_english": "The play 'Mattavilasa Prahasana' was written by Mahendra Varman I, a Pallava king from the 6th-7th century CE. He was a notable Sanskrit playwright and contributed significantly to Indian literature. Harsha is known for 'Nagananda', Jayadeva for 'Gita Govinda', and Raj Rajendra refers to later Chola rulers not associated with this play.",
      "explanation_hindi": "नाटक 'मत्तविलास प्रहसन' के रचयिता महेन्द्र वर्मन प्रथम थे, जो 6वीं-7वीं शताब्दी ईस्वी में पल्लव राजा थे। वे प्रमुख संस्कृत नाटककार थे। हर्ष 'नागानन्द' के लिए जाने जाते हैं, जयदेव 'गीता गोविन्द' के लिए, और राज राजेन्द्र बाद के चोल शासकों से संबंधित हैं।",
      "topic": "Indian Medieval History - Literature and Authors",
      "difficulty": "medium",
      "key_facts": [
        "Mahendra Varman I was a Pallava king and a prominent Sanskrit playwright.",
        "Harsha wrote 'Nagananda', Jayadeva wrote 'Gita Govinda', and Raj Rajendra refers to later Chola rulers not linked to this play."
      ],
      "ai_processed": true,
      "processed_at": "2026-01-26T04:10:39.810014"
    },
    {
      "question_hindi": "निम्नलिखित में से किस सुल्तान नेख़लीफ़ासे ‘ख़िलअत’ प्राप्त किया था?",
      "options_hindi": [
        "सुल्तान क़ुतुबुद्दीन",
        "सुल्तान इल्तुतमिश",
        "रज़िया सुल्तान",
        "सुल्तान ग़यासुद्दीन तुग़लक़"
      ],
      "option_labels": [
        "अ",
        "ब",
        "स",
        "द"
      ],
      "source": "bharatkosh",
      "page_number": 191,
      "question_number": 4,
      "subject": "इतिहास (History)",
      "language": "hindi",
      "question_english": "Which of the following sultans received 'khilat' from the Khalifa?",
      "options_english": [
        "Sultan Qutbuddin Aibak",
        "Sultan Iltutmish",
        "Razia Sultan",
        "Sultan Ghiyasuddin Tughlaq"
      ],
      "correct_answer": "b",
      "explanation_english": "Sultan Iltutmish was the first Delhi Sultan to receive the 'khilat' (a robe of honor) from the Abbasid Khalifa in 1229. This recognition symbolized the political and religious legitimacy of the Delhi Sultanate. Qutbuddin Aibak, the founder of the Delhi Sultanate, did not receive the khilat. Razia Sultan and Ghiyasuddin Tughlaq were not recognized by the Khalifa for this honor.",
      "explanation_hindi": "सुल्तान इल्तुतमिश दिल्ली सल्तनत के पहले सुल्तान थे जिन्होंने 1229 में अब्बासी खलीफा से 'खिलअत' (सम्मान की पगड़ी) प्राप्त किया। यह सम्मान दिल्ली सल्तनत की राजनीतिक और धार्मिक मान्यता के प्रतीक था। क़ुतुबुद्दीन आईबक़, जो दिल्ली सल्तनत के संस्थापक थे, ने इस सम्मान को प्राप्त नहीं किया। रजिया सुल्तान और ग़यासुद्दीन तुग़लक़ इस खिलाफत के द्वारा सम्मानित नहीं किए गए।",
      "topic": "Delhi Sultanate",
      "difficulty": "medium",
      "key_facts": [
        "Iltutmish received the khilat from the Abbasid Khalifa in 1229, legitimizing the Delhi Sultanate.",
        "Qutbuddin Aibak, the founder of the Delhi Sultanate, did not receive the khilat."
      ],
      "ai_processed": true,
      "processed_at": "2026-01-26T04:10:44.619808"
    },
    {
      "question_hindi": "‘अरबों का हेरोडोटस’ किसे कहा जाता है?",
      "options_hindi": [
        "अबू जाफ़र",
        "तबरी",
        "अलमसूदी",
        "इब्न खाल्दून"
      ],
      "option_labels": [
        "अ",
        "ब",
        "स",
        "द"
      ],
      "source": "bharatkosh",
      "page_number": 191,
      "question_number": 5,
      "subject": "इतिहास (History)",
      "language": "hindi",
      "question_english": "Who is known as the 'Herodotus of the Arabs'?",
      "options_english": [
        "Abu Jafar",
        "Tabari",
        "Al-Masudi",
        "Ibn Khaldun"
      ],
      "correct_answer": "c",
      "explanation_english": "Al-Masudi (9th-10th century) is referred to as the 'Herodotus of the Arabs' due to his comprehensive historical and geographical works. His most famous work, 'Muruj adh-Dhahab', combines history, geography, and ethnography, much like Herodotus' 'Histories'. Unlike Herodotus, however, Al-Masudi also incorporated scientific and economic data, making him a key figure in medieval Islamic historiography.",
      "explanation_hindi": "अलमसूदी (9वीं-10वीं शताब्दी) को 'अरबों का हेरोडोटस' कहा जाता है क्योंकि उनके ऐतिहासिक और भौगोलिक कार्य बहुत व्यापक थे। उनका सबसे प्रसिद्ध कार्य 'मुरुज अज-दहब' है, जो इतिहास, भूगोल और जातीय विवरणों के संग्रहण में हेरोडोटस के 'इतिहास' के समान है। हालांकि, अलमसूदी ने वैज्ञानिक और आर्थिक डेटा को भी शामिल किया, जिससे उन्हें मध्यकालीन इस्लामी इतिहासकारों के रूप में महत्वपूर्ण स्थान प्राप्त है।",
      "topic": "Medieval Arab Historians",
      "difficulty": "medium",
      "key_facts": [
        "Al-Masudi is called the 'Herodotus of the Arabs' for his encyclopedic work 'Muruj adh-Dhahab'.",
        "His works combined history, geography, and ethnography with scientific and economic data, distinguishing him from Herodotus."
      ],
      "ai_processed": true,
      "processed_at": "2026-01-26T04:10:49.452359"
    }
  ]
}